baraban/__init__.py
baraban/baraban.py
baraban-0.1.10.dist-info/METADATA
baraban-0.1.10.dist-info/WHEEL
baraban-0.1.10.dist-info/licenses/LICENSE
baraban-0.1.10.dist-info/RECORD
