Metadata-Version: 2.4
Name: baraban
Version: 0.1.10
Summary: Библиотека для проведения A/B тестов и расчета размера выборки.
Project-URL: Homepage, https://github.com/stasdikansky/baraban
Project-URL: Bug Tracker, https://github.com/stasdikansky/baraban/issues
Author: Stas Dikansky
License: MIT License
License-File: LICENSE
Classifier: License :: OSI Approved :: MIT License
Classifier: Operating System :: OS Independent
Classifier: Programming Language :: Python :: 3
Requires-Python: >=3.8
Requires-Dist: numpy>=1.20.0
Requires-Dist: otvertka>=0.1.10
Requires-Dist: pandas>=1.3.0
Requires-Dist: pydantic>=2.0.0
Requires-Dist: scipy>=1.7.0
Requires-Dist: statsmodels>=0.13.0
